dashboarder/__init__.py
dashboarder/models.py
dashboarder/tests.py
dashboarder/static/css/bootstrap.min.css
dashboarder/static/js/bootstrap.min.js
dashboarder/static/js/jquery.slim.min.js
dashboarder/static/js/popper.min.js
dashboarder/templates/admin/404.html
dashboarder/templates/admin/500.html
dashboarder/templates/admin/actions.html
dashboarder/templates/admin/app_index.html
dashboarder/templates/admin/base.html
dashboarder/templates/admin/base_site.html
dashboarder/templates/admin/change_form.html
dashboarder/templates/admin/change_list.html
dashboarder/templates/admin/change_list_results.html
dashboarder/templates/admin/date_hierarchy.html
dashboarder/templates/admin/delete_confirmation.html
dashboarder/templates/admin/delete_selected_confirmation.html
dashboarder/templates/admin/filter.html
dashboarder/templates/admin/index.html
dashboarder/templates/admin/invalid_setup.html
dashboarder/templates/admin/login.html
dashboarder/templates/admin/object_history.html
dashboarder/templates/admin/pagination.html
dashboarder/templates/admin/popup_response.html
dashboarder/templates/admin/prepopulated_fields_js.html
dashboarder/templates/admin/related_widget_wrapper.html
dashboarder/templates/admin/search_form.html
dashboarder/templates/admin/submit_line.html
dashboarder/templates/admin/auth/user/add_form.html
dashboarder/templates/admin/auth/user/change_password.html
dashboarder/templates/admin/edit_inline/stacked.html
dashboarder/templates/admin/edit_inline/tabular.html
dashboarder/templates/admin/includes/fieldset.html
dashboarder/templates/admin/includes/object_delete_summary.html
dashboarder/templates/admin/widgets/clearable_file_input.html
dashboarder/templates/admin/widgets/foreign_key_raw_id.html
dashboarder/templates/admin/widgets/many_to_many_raw_id.html
dashboarder/templates/admin/widgets/radio.html
dashboarder/templates/admin/widgets/related_widget_wrapper.html
dashboarder/templates/admin/widgets/split_datetime.html
django_dashboarder-0.1.2.dist-info/LICENSE
django_dashboarder-0.1.2.dist-info/METADATA
django_dashboarder-0.1.2.dist-info/WHEEL
django_dashboarder-0.1.2.dist-info/top_level.txt
django_dashboarder-0.1.2.dist-info/RECORD
